<?xml version="1.0" ?>
<map height="15" tileheight="32" tileset="tiles/tasumian" tilewidth="64" width="15">
<layer z="0">
<tiles>0 2 0 2 0 2 0 2 0 0    0 2 0 2 0 2 0 2 0 0    0 2 0 2 8 2 0 2 0 0    0 2 8 2 0 2 0 2 0 0    0 2 0 2 0 2 0 2 0 0    0 2 0 2 0 1 0 1 0 0    0 1 0 1 0 1 0 1 0 0    0 1 0 1 0 2 0 2 0 0    0 2 0 2 0 2 0 2 0 0    0 2 0 2 0 2 0 2 0 0    0 2 0 2 0 2 0 2 0 0    0 2 0 2 0 2 0 2 0 0    0 2 0 2 0 2 0 2 0 0    0 2 0 2 0 2 0 2 0 0    0 2 0 2 0 2 0 2 0 0    
0 2 0 2 0 2 0 2 0 0    0 2 0 2 8 2 0 2 0 0    0 2 8 2 8 2 8 2 0 0    8 2 8 2 8 2 0 2 0 0    0 2 8 2 0 2 0 2 0 0    0 2 0 2 0 1 0 1 0 0    0 1 0 1 8 1 0 1 0 0    0 1 8 1 8 2 0 2 0 0    0 2 8 2 8 2 0 2 0 0    0 2 8 2 0 2 0 2 0 0    0 2 0 2 0 2 0 2 0 0    0 2 0 2 0 2 0 2 0 0    0 2 0 2 0 2 0 2 0 0    0 2 0 2 0 2 0 2 0 0    0 2 0 2 0 2 0 2 0 0    
0 2 0 2 8 2 0 2 0 0    0 2 8 2 8 3 8 2 0 0    8 2 8 3 8 2 8 2 0 0    8 2 8 2 0 2 8 2 0 0    8 2 0 2 0 2 0 2 0 0    0 2 0 2 8 2 0 1 0 0    0 1 8 2 8 2 8 1 0 0    8 1 8 2 8 2 8 2 0 0    8 2 8 2 8 2 8 2 0 0    8 2 8 2 8 2 0 2 0 0    0 2 8 2 8 2 0 2 0 0    0 2 8 2 0 2 0 2 0 0    0 2 0 2 0 2 0 2 0 0    0 2 0 2 0 2 0 2 0 0    0 2 0 2 0 2 0 2 0 0    
0 2 0 2 0 2 8 2 0 0    8 2 0 2 0 3 8 3 0 0    8 3 0 3 8 2 8 2 0 0    8 2 8 2 8 1 0 2 0 0    0 2 8 1 8 1 0 2 0 0    0 2 8 1 0 2 8 2 0 0    8 2 0 2 8 2 8 2 0 0    8 2 8 2 8 2 8 2 0 0    8 2 8 2 0 2 8 2 0 0    8 2 0 2 8 2 8 2 0 0    8 2 8 2 8 2 8 2 0 0    8 2 8 2 0 2 0 2 0 0    0 2 0 2 0 2 0 2 0 0    0 2 0 2 0 2 0 2 0 0    0 2 0 2 0 2 0 2 0 0    
0 2 0 2 0 2 0 2 0 0    0 2 0 2 0 2 0 3 0 0    0 3 0 2 8 1 8 2 0 0    8 2 8 1 0 1 8 1 0 0    8 1 0 1 8 1 8 1 0 0    8 1 8 1 8 1 0 2 0 0    0 2 8 1 0 3 8 2 0 0    8 2 0 3 0 2 8 2 0 0    8 2 0 2 8 2 0 2 0 0    0 2 8 2 8 1 8 2 0 0    8 2 8 1 0 2 8 2 0 0    8 2 0 2 8 2 0 2 0 0    0 2 8 2 0 3 0 2 0 0    0 2 0 3 0 2 0 2 0 0    0 2 0 2 0 2 0 2 0 0    
0 2 0 2 0 2 0 2 0 0    0 2 0 2 0 1 0 2 0 0    0 2 0 1 0 1 8 1 0 0    8 1 0 1 8 1 0 1 0 0    0 1 8 1 0 3 8 1 0 0    8 1 0 3 0 2 8 1 0 0    8 1 0 2 0 2 0 3 0 0    0 3 0 2 0 2 0 2 0 0    0 2 0 2 8 2 8 2 0 0    8 2 8 2 8 1 8 1 0 0    8 1 8 1 0 2 0 2 0 0    0 2 0 2 0 2 8 2 0 0    8 2 0 2 0 3 0 3 0 0    0 3 0 3 0 2 0 2 0 0    0 2 0 2 0 2 0 2 0 0    
0 2 0 2 0 2 0 2 0 0    0 2 0 2 0 1 0 1 0 0    0 1 0 1 0 2 0 1 0 0    0 1 0 2 8 2 8 1 0 0    8 1 8 2 0 2 0 3 0 0    0 3 0 2 8 2 0 2 0 0    0 2 8 2 8 2 0 2 0 0    0 2 8 2 0 2 0 2 0 0    0 2 0 2 8 2 8 2 0 0    8 2 8 2 8 1 8 1 0 0    8 1 8 1 0 1 0 2 0 0    0 2 0 1 8 2 0 2 0 0    0 2 8 2 0 3 0 3 0 0    0 3 0 3 8 2 0 2 0 0    0 2 8 2 0 2 0 2 0 0    
0 2 0 2 0 2 0 2 0 0    0 2 0 2 8 2 0 1 0 0    0 1 8 2 8 2 0 2 0 0    0 2 8 2 0 2 8 2 0 0    8 2 0 2 8 2 0 2 0 0    0 2 8 2 8 2 8 2 0 0    8 2 8 2 8 2 8 2 0 0    8 2 8 2 0 2 0 2 0 0    0 2 0 2 8 2 8 2 0 0    8 2 8 2 0 2 8 1 0 0    8 1 0 2 0 2 0 1 0 0    0 1 0 2 0 2 8 2 0 0    8 2 0 2 8 1 0 3 0 0    0 3 8 1 8 1 8 2 0 0    8 2 8 1 8 1 0 2 0 0    
0 2 0 2 0 2 0 2 0 0    0 2 0 2 0 2 8 2 0 0    8 2 0 2 0 2 8 2 0 0    8 2 0 2 8 2 0 2 0 0    0 2 8 2 8 2 8 2 0 0    8 2 8 2 0 2 8 2 0 0    8 2 0 2 8 2 8 2 0 0    8 2 8 2 8 2 0 2 0 0    0 2 8 2 0 2 8 2 0 0    8 2 0 2 0 2 0 2 0 0    0 2 0 2 8 1 0 2 0 0    0 2 8 1 8 1 0 2 0 0    0 2 8 1 8 1 8 1 0 0    8 1 8 1 8 1 8 1 0 0    8 1 8 1 8 1 8 1 0 0    
0 2 0 2 0 2 0 2 0 0    0 2 0 2 0 2 0 2 0 0    0 2 0 2 8 2 0 2 0 0    0 2 8 2 0 1 8 2 0 0    8 2 0 1 0 2 8 2 0 0    8 2 0 2 0 2 0 2 0 0    0 2 0 2 0 2 8 2 0 0    8 2 0 2 8 2 8 2 0 0    8 2 8 2 8 2 0 2 0 0    0 2 8 2 0 3 0 2 0 0    0 2 0 3 0 2 8 1 0 0    8 1 0 2 8 2 8 1 0 0    8 1 8 2 8 2 8 1 0 0    8 1 8 2 8 2 8 1 0 0    8 1 8 2 8 2 8 1 0 0    
0 2 0 2 0 2 0 2 0 0    0 2 0 2 0 2 0 2 0 0    0 2 0 2 0 2 8 2 0 0    8 2 0 2 8 3 0 1 0 0    0 1 8 3 0 1 0 2 0 0    0 2 0 1 8 2 0 2 0 0    0 2 8 2 8 2 0 2 0 0    0 2 8 2 8 2 8 2 0 0    8 2 8 2 8 3 8 2 0 0    8 2 8 3 8 3 0 3 0 0    0 3 8 3 8 1 0 2 0 0    0 2 8 1 8 2 8 2 0 0    8 2 8 2 8 2 8 2 0 0    8 2 8 2 0 2 8 2 0 0    8 2 0 2 0 2 8 2 0 0    
0 2 0 2 0 2 0 2 0 0    0 2 0 2 0 2 0 2 0 0    0 2 0 2 0 2 0 2 0 0    0 2 0 2 0 3 8 3 0 0    8 3 0 3 0 1 0 1 0 0    0 1 0 1 8 1 8 2 0 0    8 2 8 1 0 1 8 2 0 0    8 2 0 1 8 1 8 2 0 0    8 2 8 1 8 1 8 3 0 0    8 3 8 1 8 2 8 3 0 0    8 3 8 2 0 2 8 1 0 0    8 1 0 2 8 2 8 2 0 0    8 2 8 2 0 2 8 2 0 0    8 2 0 2 0 2 0 2 0 0    0 2 0 2 0 2 0 2 0 0    
0 2 0 2 0 2 0 2 0 0    0 2 0 2 0 2 0 2 0 0    0 2 0 2 0 2 0 2 0 0    0 2 0 2 0 2 0 3 0 0    0 3 0 2 0 2 0 1 0 0    0 1 0 2 0 1 8 1 0 0    8 1 0 1 0 1 0 1 0 0    0 1 0 1 0 1 8 1 0 0    8 1 0 1 0 3 8 1 0 0    8 1 0 3 0 2 8 2 0 0    8 2 0 2 0 2 0 2 0 0    0 2 0 2 8 3 8 2 0 0    8 2 8 3 0 3 0 2 0 0    0 2 0 3 0 2 0 2 0 0    0 2 0 2 0 2 0 2 0 0    
0 2 0 2 0 2 0 2 0 0    0 2 0 2 0 2 0 2 0 0    0 2 0 2 0 2 0 2 0 0    0 2 0 2 8 2 0 2 0 0    0 2 8 2 8 2 0 2 0 0    0 2 8 2 0 2 0 1 0 0    0 1 0 2 0 2 0 1 0 0    0 1 0 2 0 2 0 1 0 0    0 1 0 2 0 2 0 3 0 0    0 3 0 2 0 2 0 2 0 0    0 2 0 2 0 2 0 2 0 0    0 2 0 2 0 2 8 3 0 0    8 3 0 2 0 2 0 3 0 0    0 3 0 2 0 2 0 2 0 0    0 2 0 2 0 2 0 2 0 0    
0 2 0 2 0 2 0 2 0 0    0 2 0 2 0 2 0 2 0 0    0 2 0 2 0 2 0 2 0 0    0 2 0 2 0 2 8 2 0 0    8 2 0 2 0 2 8 2 0 0    8 2 0 2 0 2 0 2 0 0    0 2 0 2 0 2 0 2 0 0    0 2 0 2 0 2 0 2 0 0    0 2 0 2 0 2 0 2 0 0    0 2 0 2 0 2 0 2 0 0    0 2 0 2 0 2 0 2 0 0    0 2 0 2 0 2 0 2 0 0    0 2 0 2 0 2 0 2 0 0    0 2 0 2 0 2 0 2 0 0    0 2 0 2 0 2 0 2 0 0    
</tiles>
<staticobject mask="masks/tree.png" name="tree" sprite="sprites/tree.png" tilex="4" tiley="5"/>
<staticobject mask="masks/tree.png" name="tree" sprite="sprites/tree.png" tilex="8" tiley="10"/>
<staticobject mask="masks/tree.png" name="tree" sprite="sprites/tree.png" tilex="2" tiley="12"/>
<staticobject mask="masks/tree.png" name="tree" sprite="sprites/tree.png" tilex="12" tiley="14"/>
<staticobject mask="masks/tree.png" name="tree" sprite="sprites/tree.png" tilex="12" tiley="4"/>

<staticobject mask="masks/bush.png" name="bush" sprite="sprites/bush.png" tilex="2" tiley="2"/>
<staticobject mask="masks/bush.png" name="bush" sprite="sprites/bush.png" tilex="6" tiley="9"/>
<staticobject mask="masks/bush.png" name="bush" sprite="sprites/bush.png" tilex="13" tiley="12"/>
<staticobject mask="masks/bush.png" name="bush" sprite="sprites/bush.png" tilex="4" tiley="2"/>

<!-- If we have already talked to krelshar, and not killed this wolf already, there's a wolf. -->
<if code="import party;partyManager=party.getPartyManager()" cond="partyManager.hasRecord('tasumian_met_krelshar') and not partyManager.hasRecord('tasumian_killed_wolf3')">
    <staticobject name="wolf3" config="locations/tasumian/wolf.xml" tilex="6" tiley="10"/>
</if>

<!-- Way east. -->
<area tilex1="5" tilex2="8" tiley1="0" tiley2="1">
import party, annchientamathManager = annchienta.getMathManager()
partyManager = party.getPartyManager()
partyManager.changeMap( &quot;locations/tasumian/&quot;+str(mathManager.randInt(3))+&quot;-1.xml&quot;, annchienta.Point( annchienta.TilePoint, 8, 13 ) )
</area>

<!-- Way south. -->
<area tilex1="14" tilex2="15" tiley1="7" tiley2="10">
import party, annchientamathManager = annchienta.getMathManager()
partyManager = party.getPartyManager()
partyManager.changeMap( &quot;locations/tasumian/1-&quot;+str(mathManager.randInt(3))+&quot;.xml&quot;, annchienta.Point( annchienta.TilePoint, 2, 7 ) )
</area>

</layer>
<onload script="locations/tasumian/onload.py"/>
</map>